setup.py
pywhoisclient/_Other.py
pywhoisclient/_WhoisParser.py
pywhoisclient/_WhoisParserEx.py
pywhoisclient/_WhoisSearchService.py
pywhoisclient/_WhoisService.py
pywhoisclient/__init__.py
pywhoisclient/__main__.py
pywhoisclient/error.py
pywhoisclient.egg-info/PKG-INFO
pywhoisclient.egg-info/SOURCES.txt
pywhoisclient.egg-info/dependency_links.txt
pywhoisclient.egg-info/top_level.txt
tests/__init__.py