Metadata-Version: 1.1
Name: pywhoisclient
Version: 0.14
Summary: An demonstration of how to make whois reqest
Home-page: https://github.com/vit1251/pywhoisclient
Author: Vitold Sedyshev
Author-email: vit1251@gmail.com
License: MIT
Keywords: whois client
Platform: UNKNOWN
Classifier: Development Status :: 3 - Alpha
Classifier: Topic :: Utilities
Classifier: License :: OSI Approved :: BSD License
